[
    {
        "transactionName": "UC00_Login",
        "rawStartTime": 1548685033946,
        "rawEndTime": 1548685034366
    },
    {
        "transactionName": "UC00_TR01_Flights",
        "rawStartTime": 1548685034378,
        "rawEndTime": 1548685034574
    },
    {
        "transactionName": "UC01_TR01_Find_Flight",
        "rawStartTime": 1548685034581,
        "rawEndTime": 1548685034692
    },
    {
        "transactionName": "UC00_TR01_Sign_Off",
        "rawStartTime": 1548685034712,
        "rawEndTime": 1548685034984
    }
]